MANIFEST.in
README.rst
VERSION
requirements.txt
setup.cfg
setup.py
test-requirements.txt
ecsminion/__init__.py
ecsminion.egg-info/PKG-INFO
ecsminion.egg-info/SOURCES.txt
ecsminion.egg-info/dependency_links.txt
ecsminion.egg-info/not-zip-safe
ecsminion.egg-info/requires.txt
ecsminion.egg-info/top_level.txt
ecsminion/api/__init__.py
ecsminion/api/authentication.py
ecsminion/api/configuration/__init__.py
ecsminion/api/configuration/certificate.py
ecsminion/api/configuration/configuration_properties.py
ecsminion/api/configuration/licensing.py
ecsminion/api/geo_replication/__init__.py
ecsminion/api/geo_replication/replication_group.py
ecsminion/api/geo_replication/temporary_failed_zone.py
ecsminion/api/metering/__init__.py
ecsminion/api/metering/billing.py
ecsminion/api/monitoring/__init__.py
ecsminion/api/monitoring/capacity.py
ecsminion/api/monitoring/dashboard.py
ecsminion/api/monitoring/events.py
ecsminion/api/multitenancy/__init__.py
ecsminion/api/multitenancy/namespace.py
ecsminion/api/provisioning/__init__.py
ecsminion/api/provisioning/base_url.py
ecsminion/api/provisioning/bucket.py
ecsminion/api/provisioning/data_store.py
ecsminion/api/provisioning/node.py
ecsminion/api/provisioning/storage_pool.py
ecsminion/api/provisioning/virtual_data_center.py
ecsminion/api/support/__init__.py
ecsminion/api/support/call_home.py
ecsminion/api/undocumented/__init__.py
ecsminion/api/undocumented/user_info.py
ecsminion/api/user_management/__init__.py
ecsminion/api/user_management/authentication_provider.py
ecsminion/api/user_management/secret_key.py
ecsminion/api/user_management/secret_key_self_service.py
ecsminion/api/user_management/user_management.py
ecsminion/api/user_management/user_object.py
ecsminion/util/__init__.py
ecsminion/util/common.py
ecsminion/util/exceptions.py
ecsminion/util/token_request.py
tests/__init__.py
tests/api/__init__.py
tests/api/provisioning/__init__.py
tests/api/provisioning/node_test.py
tests/util/__init__.py
tests/util/common_test.py
tests/util/token_request_test.py