Metadata-Version: 1.0
Name: ecsminion
Version: 0.7.6
Summary: A library for interacting with the ECS 2.x Management API
Home-page: https://github.com/chadlung/ecsminion
Author: Chad Lung
Author-email: chad.lung@gmail.com
License: UNKNOWN
Keywords: ecsminion
Platform: UNKNOWN
